cloud_browser_use_mcp_server/__init__.py
cloud_browser_use_mcp_server/__main__.py
cloud_browser_use_mcp_server/server.py
cloud_browser_use_mcp_server-0.2.0.dist-info/METADATA
cloud_browser_use_mcp_server-0.2.0.dist-info/WHEEL
cloud_browser_use_mcp_server-0.2.0.dist-info/entry_points.txt
cloud_browser_use_mcp_server-0.2.0.dist-info/licenses/LICENSE
cloud_browser_use_mcp_server-0.2.0.dist-info/RECORD
