Metadata-Version: 2.4
Name: cloud-browser-use-mcp-server
Version: 0.2.0
Summary: An unofficial Model Context Protocol server for automating browser tasks using Browser Use API. This package is not provided or endorsed by Browser Use.
Project-URL: Repository, https://github.com/mhazarabad/browser-use-mcp
Project-URL: Documentation, https://github.com/mhazarabad/browser-use-mcp#readme
Project-URL: Issues, https://github.com/mhazarabad/browser-use-mcp/issues
Author-email: Hadi Hazarabad <mhazarabad@gmail.com>
License: MIT
License-File: LICENSE
Classifier: Development Status :: 4 - Beta
Classifier: Intended Audience :: Developers
Classifier: License :: OSI Approved :: MIT License
Classifier: Operating System :: OS Independent
Classifier: Programming Language :: Python :: 3
Classifier: Programming Language :: Python :: 3.10
Classifier: Programming Language :: Python :: 3.11
Classifier: Topic :: Software Development :: Libraries :: Python Modules
Requires-Python: >=3.10
Requires-Dist: click>=8.0.0
Requires-Dist: httpx>=0.24.0
Requires-Dist: mcp>=1.0.0
Requires-Dist: pydantic>=2.0.0
